
{"items":[{"name":"CycloneDX","href":"CycloneDX.html","topicHref":"CycloneDX.html","topicUid":"CycloneDX","type":"Namespace","items":[{"name":"BomUtils","href":"CycloneDX.BomUtils.html","topicHref":"CycloneDX.BomUtils.html","topicUid":"CycloneDX.BomUtils","type":"Class"},{"name":"MediaTypes","href":"CycloneDX.MediaTypes.html","topicHref":"CycloneDX.MediaTypes.html","topicUid":"CycloneDX.MediaTypes","type":"Class"},{"name":"SerializationFormat","href":"CycloneDX.SerializationFormat.html","topicHref":"CycloneDX.SerializationFormat.html","topicUid":"CycloneDX.SerializationFormat","type":"Enum"},{"name":"SpecificationVersion","href":"CycloneDX.SpecificationVersion.html","topicHref":"CycloneDX.SpecificationVersion.html","topicUid":"CycloneDX.SpecificationVersion","type":"Enum"},{"name":"SpecificationVersionHelpers","href":"CycloneDX.SpecificationVersionHelpers.html","topicHref":"CycloneDX.SpecificationVersionHelpers.html","topicUid":"CycloneDX.SpecificationVersionHelpers","type":"Class"}]},{"name":"CycloneDX.Core.Models","href":"CycloneDX.Core.Models.html","topicHref":"CycloneDX.Core.Models.html","topicUid":"CycloneDX.Core.Models","type":"Namespace","items":[{"name":"AlgorithmMode","href":"CycloneDX.Core.Models.AlgorithmMode.html","topicHref":"CycloneDX.Core.Models.AlgorithmMode.html","topicUid":"CycloneDX.Core.Models.AlgorithmMode","type":"Enum"},{"name":"AlgorithmProperties","href":"CycloneDX.Core.Models.AlgorithmProperties.html","topicHref":"CycloneDX.Core.Models.AlgorithmProperties.html","topicUid":"CycloneDX.Core.Models.AlgorithmProperties","type":"Class"},{"name":"AssetType","href":"CycloneDX.Core.Models.AssetType.html","topicHref":"CycloneDX.Core.Models.AssetType.html","topicUid":"CycloneDX.Core.Models.AssetType","type":"Enum"},{"name":"CertificateProperties","href":"CycloneDX.Core.Models.CertificateProperties.html","topicHref":"CycloneDX.Core.Models.CertificateProperties.html","topicUid":"CycloneDX.Core.Models.CertificateProperties","type":"Class"},{"name":"CertificationLevel","href":"CycloneDX.Core.Models.CertificationLevel.html","topicHref":"CycloneDX.Core.Models.CertificationLevel.html","topicUid":"CycloneDX.Core.Models.CertificationLevel","type":"Enum"},{"name":"CertificationLevelExtensions","href":"CycloneDX.Core.Models.CertificationLevelExtensions.html","topicHref":"CycloneDX.Core.Models.CertificationLevelExtensions.html","topicUid":"CycloneDX.Core.Models.CertificationLevelExtensions","type":"Class"},{"name":"CipherSuite","href":"CycloneDX.Core.Models.CipherSuite.html","topicHref":"CycloneDX.Core.Models.CipherSuite.html","topicUid":"CycloneDX.Core.Models.CipherSuite","type":"Class"},{"name":"CipherSuiteCollection","href":"CycloneDX.Core.Models.CipherSuiteCollection.html","topicHref":"CycloneDX.Core.Models.CipherSuiteCollection.html","topicUid":"CycloneDX.Core.Models.CipherSuiteCollection","type":"Class"},{"name":"CryptoFunction","href":"CycloneDX.Core.Models.CryptoFunction.html","topicHref":"CycloneDX.Core.Models.CryptoFunction.html","topicUid":"CycloneDX.Core.Models.CryptoFunction","type":"Enum"},{"name":"CryptoProperties","href":"CycloneDX.Core.Models.CryptoProperties.html","topicHref":"CycloneDX.Core.Models.CryptoProperties.html","topicUid":"CycloneDX.Core.Models.CryptoProperties","type":"Class"},{"name":"ExecutionEnvironment","href":"CycloneDX.Core.Models.ExecutionEnvironment.html","topicHref":"CycloneDX.Core.Models.ExecutionEnvironment.html","topicUid":"CycloneDX.Core.Models.ExecutionEnvironment","type":"Enum"},{"name":"Ikev2TransformTypes","href":"CycloneDX.Core.Models.Ikev2TransformTypes.html","topicHref":"CycloneDX.Core.Models.Ikev2TransformTypes.html","topicUid":"CycloneDX.Core.Models.Ikev2TransformTypes","type":"Class"},{"name":"ImplementationPlatform","href":"CycloneDX.Core.Models.ImplementationPlatform.html","topicHref":"CycloneDX.Core.Models.ImplementationPlatform.html","topicUid":"CycloneDX.Core.Models.ImplementationPlatform","type":"Enum"},{"name":"KeyState","href":"CycloneDX.Core.Models.KeyState.html","topicHref":"CycloneDX.Core.Models.KeyState.html","topicUid":"CycloneDX.Core.Models.KeyState","type":"Enum"},{"name":"PaddingScheme","href":"CycloneDX.Core.Models.PaddingScheme.html","topicHref":"CycloneDX.Core.Models.PaddingScheme.html","topicUid":"CycloneDX.Core.Models.PaddingScheme","type":"Enum"},{"name":"Primitive","href":"CycloneDX.Core.Models.Primitive.html","topicHref":"CycloneDX.Core.Models.Primitive.html","topicUid":"CycloneDX.Core.Models.Primitive","type":"Enum"},{"name":"ProtocolProperties","href":"CycloneDX.Core.Models.ProtocolProperties.html","topicHref":"CycloneDX.Core.Models.ProtocolProperties.html","topicUid":"CycloneDX.Core.Models.ProtocolProperties","type":"Class"},{"name":"ProtocolType","href":"CycloneDX.Core.Models.ProtocolType.html","topicHref":"CycloneDX.Core.Models.ProtocolType.html","topicUid":"CycloneDX.Core.Models.ProtocolType","type":"Enum"},{"name":"RelatedCryptoMaterialProperties","href":"CycloneDX.Core.Models.RelatedCryptoMaterialProperties.html","topicHref":"CycloneDX.Core.Models.RelatedCryptoMaterialProperties.html","topicUid":"CycloneDX.Core.Models.RelatedCryptoMaterialProperties","type":"Class"},{"name":"RelatedCryptoMaterialType","href":"CycloneDX.Core.Models.RelatedCryptoMaterialType.html","topicHref":"CycloneDX.Core.Models.RelatedCryptoMaterialType.html","topicUid":"CycloneDX.Core.Models.RelatedCryptoMaterialType","type":"Enum"},{"name":"SecuredBy","href":"CycloneDX.Core.Models.SecuredBy.html","topicHref":"CycloneDX.Core.Models.SecuredBy.html","topicUid":"CycloneDX.Core.Models.SecuredBy","type":"Class"}]},{"name":"CycloneDX.Exceptions","href":"CycloneDX.Exceptions.html","topicHref":"CycloneDX.Exceptions.html","topicUid":"CycloneDX.Exceptions","type":"Namespace","items":[{"name":"UnsupportedFormatSpecificationVersionException","href":"CycloneDX.Exceptions.UnsupportedFormatSpecificationVersionException.html","topicHref":"CycloneDX.Exceptions.UnsupportedFormatSpecificationVersionException.html","topicUid":"CycloneDX.Exceptions.UnsupportedFormatSpecificationVersionException","type":"Class"}]},{"name":"CycloneDX.Json","href":"CycloneDX.Json.html","topicHref":"CycloneDX.Json.html","topicUid":"CycloneDX.Json","type":"Namespace","items":[{"name":"Serializer","href":"CycloneDX.Json.Serializer.html","topicHref":"CycloneDX.Json.Serializer.html","topicUid":"CycloneDX.Json.Serializer","type":"Class"},{"name":"Utils","href":"CycloneDX.Json.Utils.html","topicHref":"CycloneDX.Json.Utils.html","topicUid":"CycloneDX.Json.Utils","type":"Class"},{"name":"Validator","href":"CycloneDX.Json.Validator.html","topicHref":"CycloneDX.Json.Validator.html","topicUid":"CycloneDX.Json.Validator","type":"Class"}]},{"name":"CycloneDX.Json.Converters","href":"CycloneDX.Json.Converters.html","topicHref":"CycloneDX.Json.Converters.html","topicUid":"CycloneDX.Json.Converters","type":"Namespace","items":[{"name":"DataflowSourceDestinationConverter","href":"CycloneDX.Json.Converters.DataflowSourceDestinationConverter.html","topicHref":"CycloneDX.Json.Converters.DataflowSourceDestinationConverter.html","topicUid":"CycloneDX.Json.Converters.DataflowSourceDestinationConverter","type":"Class"},{"name":"DatasetChoicesConverter","href":"CycloneDX.Json.Converters.DatasetChoicesConverter.html","topicHref":"CycloneDX.Json.Converters.DatasetChoicesConverter.html","topicUid":"CycloneDX.Json.Converters.DatasetChoicesConverter","type":"Class"},{"name":"DateTimeConverter","href":"CycloneDX.Json.Converters.DateTimeConverter.html","topicHref":"CycloneDX.Json.Converters.DateTimeConverter.html","topicUid":"CycloneDX.Json.Converters.DateTimeConverter","type":"Class"},{"name":"DependencyConverter","href":"CycloneDX.Json.Converters.DependencyConverter.html","topicHref":"CycloneDX.Json.Converters.DependencyConverter.html","topicUid":"CycloneDX.Json.Converters.DependencyConverter","type":"Class"},{"name":"EnumMemberConverter<T>","href":"CycloneDX.Json.Converters.EnumMemberConverter-1.html","topicHref":"CycloneDX.Json.Converters.EnumMemberConverter-1.html","topicUid":"CycloneDX.Json.Converters.EnumMemberConverter`1","type":"Class"},{"name":"EnvironmentVarChoiceConverter","href":"CycloneDX.Json.Converters.EnvironmentVarChoiceConverter.html","topicHref":"CycloneDX.Json.Converters.EnvironmentVarChoiceConverter.html","topicUid":"CycloneDX.Json.Converters.EnvironmentVarChoiceConverter","type":"Class"},{"name":"EvidenceIdentityListConverter","href":"CycloneDX.Json.Converters.EvidenceIdentityListConverter.html","topicHref":"CycloneDX.Json.Converters.EvidenceIdentityListConverter.html","topicUid":"CycloneDX.Json.Converters.EvidenceIdentityListConverter","type":"Class"},{"name":"HyphenEnumConverter<T>","href":"CycloneDX.Json.Converters.HyphenEnumConverter-1.html","topicHref":"CycloneDX.Json.Converters.HyphenEnumConverter-1.html","topicUid":"CycloneDX.Json.Converters.HyphenEnumConverter`1","type":"Class"},{"name":"KeepCaseHyphenEnumConverter<T>","href":"CycloneDX.Json.Converters.KeepCaseHyphenEnumConverter-1.html","topicHref":"CycloneDX.Json.Converters.KeepCaseHyphenEnumConverter-1.html","topicUid":"CycloneDX.Json.Converters.KeepCaseHyphenEnumConverter`1","type":"Class"},{"name":"RefObject","href":"CycloneDX.Json.Converters.RefObject.html","topicHref":"CycloneDX.Json.Converters.RefObject.html","topicUid":"CycloneDX.Json.Converters.RefObject","type":"Class"},{"name":"ScoreMethodConverter","href":"CycloneDX.Json.Converters.ScoreMethodConverter.html","topicHref":"CycloneDX.Json.Converters.ScoreMethodConverter.html","topicUid":"CycloneDX.Json.Converters.ScoreMethodConverter","type":"Class"},{"name":"SignatureChoiceConverter","href":"CycloneDX.Json.Converters.SignatureChoiceConverter.html","topicHref":"CycloneDX.Json.Converters.SignatureChoiceConverter.html","topicUid":"CycloneDX.Json.Converters.SignatureChoiceConverter","type":"Class"},{"name":"ToolChoicesConverter","href":"CycloneDX.Json.Converters.ToolChoicesConverter.html","topicHref":"CycloneDX.Json.Converters.ToolChoicesConverter.html","topicUid":"CycloneDX.Json.Converters.ToolChoicesConverter","type":"Class"},{"name":"UnderscoreEnumConverter<T>","href":"CycloneDX.Json.Converters.UnderscoreEnumConverter-1.html","topicHref":"CycloneDX.Json.Converters.UnderscoreEnumConverter-1.html","topicUid":"CycloneDX.Json.Converters.UnderscoreEnumConverter`1","type":"Class"}]},{"name":"CycloneDX.Models","href":"CycloneDX.Models.html","topicHref":"CycloneDX.Models.html","topicUid":"CycloneDX.Models","type":"Namespace","items":[{"name":"ActivityType","href":"CycloneDX.Models.ActivityType.html","topicHref":"CycloneDX.Models.ActivityType.html","topicUid":"CycloneDX.Models.ActivityType","type":"Enum"},{"name":"Affirmation","href":"CycloneDX.Models.Affirmation.html","topicHref":"CycloneDX.Models.Affirmation.html","topicUid":"CycloneDX.Models.Affirmation","type":"Class"},{"name":"Annotation","href":"CycloneDX.Models.Annotation.html","topicHref":"CycloneDX.Models.Annotation.html","topicUid":"CycloneDX.Models.Annotation","type":"Class"},{"name":"Annotation.XmlAnnotationSubject","href":"CycloneDX.Models.Annotation.XmlAnnotationSubject.html","topicHref":"CycloneDX.Models.Annotation.XmlAnnotationSubject.html","topicUid":"CycloneDX.Models.Annotation.XmlAnnotationSubject","type":"Class"},{"name":"AnnotatorChoice","href":"CycloneDX.Models.AnnotatorChoice.html","topicHref":"CycloneDX.Models.AnnotatorChoice.html","topicUid":"CycloneDX.Models.AnnotatorChoice","type":"Class"},{"name":"Assessor","href":"CycloneDX.Models.Assessor.html","topicHref":"CycloneDX.Models.Assessor.html","topicUid":"CycloneDX.Models.Assessor","type":"Class"},{"name":"AttachedText","href":"CycloneDX.Models.AttachedText.html","topicHref":"CycloneDX.Models.AttachedText.html","topicUid":"CycloneDX.Models.AttachedText","type":"Class"},{"name":"Attestation","href":"CycloneDX.Models.Attestation.html","topicHref":"CycloneDX.Models.Attestation.html","topicUid":"CycloneDX.Models.Attestation","type":"Class"},{"name":"Bom","href":"CycloneDX.Models.Bom.html","topicHref":"CycloneDX.Models.Bom.html","topicUid":"CycloneDX.Models.Bom","type":"Class"},{"name":"CO2Unit","href":"CycloneDX.Models.CO2Unit.html","topicHref":"CycloneDX.Models.CO2Unit.html","topicUid":"CycloneDX.Models.CO2Unit","type":"Enum"},{"name":"Callstack","href":"CycloneDX.Models.Callstack.html","topicHref":"CycloneDX.Models.Callstack.html","topicUid":"CycloneDX.Models.Callstack","type":"Class"},{"name":"Callstack.Frame","href":"CycloneDX.Models.Callstack.Frame.html","topicHref":"CycloneDX.Models.Callstack.Frame.html","topicUid":"CycloneDX.Models.Callstack.Frame","type":"Class"},{"name":"Claim","href":"CycloneDX.Models.Claim.html","topicHref":"CycloneDX.Models.Claim.html","topicUid":"CycloneDX.Models.Claim","type":"Class"},{"name":"Co2Measure","href":"CycloneDX.Models.Co2Measure.html","topicHref":"CycloneDX.Models.Co2Measure.html","topicUid":"CycloneDX.Models.Co2Measure","type":"Class"},{"name":"Command","href":"CycloneDX.Models.Command.html","topicHref":"CycloneDX.Models.Command.html","topicUid":"CycloneDX.Models.Command","type":"Class"},{"name":"Commit","href":"CycloneDX.Models.Commit.html","topicHref":"CycloneDX.Models.Commit.html","topicUid":"CycloneDX.Models.Commit","type":"Class"},{"name":"Component","href":"CycloneDX.Models.Component.html","topicHref":"CycloneDX.Models.Component.html","topicUid":"CycloneDX.Models.Component","type":"Class"},{"name":"Component.Classification","href":"CycloneDX.Models.Component.Classification.html","topicHref":"CycloneDX.Models.Component.Classification.html","topicUid":"CycloneDX.Models.Component.Classification","type":"Enum"},{"name":"Component.ComponentScope","href":"CycloneDX.Models.Component.ComponentScope.html","topicHref":"CycloneDX.Models.Component.ComponentScope.html","topicUid":"CycloneDX.Models.Component.ComponentScope","type":"Enum"},{"name":"Composition","href":"CycloneDX.Models.Composition.html","topicHref":"CycloneDX.Models.Composition.html","topicUid":"CycloneDX.Models.Composition","type":"Class"},{"name":"Composition.AggregateType","href":"CycloneDX.Models.Composition.AggregateType.html","topicHref":"CycloneDX.Models.Composition.AggregateType.html","topicUid":"CycloneDX.Models.Composition.AggregateType","type":"Enum"},{"name":"Confidence","href":"CycloneDX.Models.Confidence.html","topicHref":"CycloneDX.Models.Confidence.html","topicUid":"CycloneDX.Models.Confidence","type":"Class"},{"name":"Conformance","href":"CycloneDX.Models.Conformance.html","topicHref":"CycloneDX.Models.Conformance.html","topicUid":"CycloneDX.Models.Conformance","type":"Class"},{"name":"Data","href":"CycloneDX.Models.Data.html","topicHref":"CycloneDX.Models.Data.html","topicUid":"CycloneDX.Models.Data","type":"Class"},{"name":"Data.DataContents","href":"CycloneDX.Models.Data.DataContents.html","topicHref":"CycloneDX.Models.Data.DataContents.html","topicUid":"CycloneDX.Models.Data.DataContents","type":"Class"},{"name":"Data.DataType","href":"CycloneDX.Models.Data.DataType.html","topicHref":"CycloneDX.Models.Data.DataType.html","topicUid":"CycloneDX.Models.Data.DataType","type":"Enum"},{"name":"DataClassification","href":"CycloneDX.Models.DataClassification.html","topicHref":"CycloneDX.Models.DataClassification.html","topicUid":"CycloneDX.Models.DataClassification","type":"Class"},{"name":"DataFlow","href":"CycloneDX.Models.DataFlow.html","topicHref":"CycloneDX.Models.DataFlow.html","topicUid":"CycloneDX.Models.DataFlow","type":"Class"},{"name":"DataFlowDirection","href":"CycloneDX.Models.DataFlowDirection.html","topicHref":"CycloneDX.Models.DataFlowDirection.html","topicUid":"CycloneDX.Models.DataFlowDirection","type":"Enum"},{"name":"DataGovernance","href":"CycloneDX.Models.DataGovernance.html","topicHref":"CycloneDX.Models.DataGovernance.html","topicUid":"CycloneDX.Models.DataGovernance","type":"Class"},{"name":"DataflowSourceDestination","href":"CycloneDX.Models.DataflowSourceDestination.html","topicHref":"CycloneDX.Models.DataflowSourceDestination.html","topicUid":"CycloneDX.Models.DataflowSourceDestination","type":"Class"},{"name":"DatasetChoice","href":"CycloneDX.Models.DatasetChoice.html","topicHref":"CycloneDX.Models.DatasetChoice.html","topicUid":"CycloneDX.Models.DatasetChoice","type":"Class"},{"name":"DatasetChoices","href":"CycloneDX.Models.DatasetChoices.html","topicHref":"CycloneDX.Models.DatasetChoices.html","topicUid":"CycloneDX.Models.DatasetChoices","type":"Class"},{"name":"DeclarationData","href":"CycloneDX.Models.DeclarationData.html","topicHref":"CycloneDX.Models.DeclarationData.html","topicUid":"CycloneDX.Models.DeclarationData","type":"Class"},{"name":"DeclarationDataContents","href":"CycloneDX.Models.DeclarationDataContents.html","topicHref":"CycloneDX.Models.DeclarationDataContents.html","topicUid":"CycloneDX.Models.DeclarationDataContents","type":"Class"},{"name":"Declarations","href":"CycloneDX.Models.Declarations.html","topicHref":"CycloneDX.Models.Declarations.html","topicUid":"CycloneDX.Models.Declarations","type":"Class"},{"name":"DeclarationsEvidence","href":"CycloneDX.Models.DeclarationsEvidence.html","topicHref":"CycloneDX.Models.DeclarationsEvidence.html","topicUid":"CycloneDX.Models.DeclarationsEvidence","type":"Class"},{"name":"Definitions","href":"CycloneDX.Models.Definitions.html","topicHref":"CycloneDX.Models.Definitions.html","topicUid":"CycloneDX.Models.Definitions","type":"Class"},{"name":"Dependency","href":"CycloneDX.Models.Dependency.html","topicHref":"CycloneDX.Models.Dependency.html","topicUid":"CycloneDX.Models.Dependency","type":"Class"},{"name":"Diff","href":"CycloneDX.Models.Diff.html","topicHref":"CycloneDX.Models.Diff.html","topicUid":"CycloneDX.Models.Diff","type":"Class"},{"name":"EnergyConsumption","href":"CycloneDX.Models.EnergyConsumption.html","topicHref":"CycloneDX.Models.EnergyConsumption.html","topicUid":"CycloneDX.Models.EnergyConsumption","type":"Class"},{"name":"EnergyMeasure","href":"CycloneDX.Models.EnergyMeasure.html","topicHref":"CycloneDX.Models.EnergyMeasure.html","topicUid":"CycloneDX.Models.EnergyMeasure","type":"Class"},{"name":"EnergyProvider","href":"CycloneDX.Models.EnergyProvider.html","topicHref":"CycloneDX.Models.EnergyProvider.html","topicUid":"CycloneDX.Models.EnergyProvider","type":"Class"},{"name":"EnergySource","href":"CycloneDX.Models.EnergySource.html","topicHref":"CycloneDX.Models.EnergySource.html","topicUid":"CycloneDX.Models.EnergySource","type":"Enum"},{"name":"EnergyUnit","href":"CycloneDX.Models.EnergyUnit.html","topicHref":"CycloneDX.Models.EnergyUnit.html","topicUid":"CycloneDX.Models.EnergyUnit","type":"Enum"},{"name":"EnvironmentVarChoice","href":"CycloneDX.Models.EnvironmentVarChoice.html","topicHref":"CycloneDX.Models.EnvironmentVarChoice.html","topicUid":"CycloneDX.Models.EnvironmentVarChoice","type":"Class"},{"name":"EnvironmentVarChoices","href":"CycloneDX.Models.EnvironmentVarChoices.html","topicHref":"CycloneDX.Models.EnvironmentVarChoices.html","topicUid":"CycloneDX.Models.EnvironmentVarChoices","type":"Class"},{"name":"Event","href":"CycloneDX.Models.Event.html","topicHref":"CycloneDX.Models.Event.html","topicUid":"CycloneDX.Models.Event","type":"Class"},{"name":"Evidence","href":"CycloneDX.Models.Evidence.html","topicHref":"CycloneDX.Models.Evidence.html","topicUid":"CycloneDX.Models.Evidence","type":"Class"},{"name":"EvidenceCopyright","href":"CycloneDX.Models.EvidenceCopyright.html","topicHref":"CycloneDX.Models.EvidenceCopyright.html","topicUid":"CycloneDX.Models.EvidenceCopyright","type":"Class"},{"name":"EvidenceIdentity","href":"CycloneDX.Models.EvidenceIdentity.html","topicHref":"CycloneDX.Models.EvidenceIdentity.html","topicUid":"CycloneDX.Models.EvidenceIdentity","type":"Class"},{"name":"EvidenceIdentity.EvidenceFieldType","href":"CycloneDX.Models.EvidenceIdentity.EvidenceFieldType.html","topicHref":"CycloneDX.Models.EvidenceIdentity.EvidenceFieldType.html","topicUid":"CycloneDX.Models.EvidenceIdentity.EvidenceFieldType","type":"Enum"},{"name":"EvidenceIdentityList","href":"CycloneDX.Models.EvidenceIdentityList.html","topicHref":"CycloneDX.Models.EvidenceIdentityList.html","topicUid":"CycloneDX.Models.EvidenceIdentityList","type":"Class"},{"name":"EvidenceMethods","href":"CycloneDX.Models.EvidenceMethods.html","topicHref":"CycloneDX.Models.EvidenceMethods.html","topicUid":"CycloneDX.Models.EvidenceMethods","type":"Class"},{"name":"EvidenceMethods.EvidenceTechnique","href":"CycloneDX.Models.EvidenceMethods.EvidenceTechnique.html","topicHref":"CycloneDX.Models.EvidenceMethods.EvidenceTechnique.html","topicUid":"CycloneDX.Models.EvidenceMethods.EvidenceTechnique","type":"Enum"},{"name":"EvidenceOccurrence","href":"CycloneDX.Models.EvidenceOccurrence.html","topicHref":"CycloneDX.Models.EvidenceOccurrence.html","topicUid":"CycloneDX.Models.EvidenceOccurrence","type":"Class"},{"name":"EvidenceTools","href":"CycloneDX.Models.EvidenceTools.html","topicHref":"CycloneDX.Models.EvidenceTools.html","topicUid":"CycloneDX.Models.EvidenceTools","type":"Class"},{"name":"ExternalReference","href":"CycloneDX.Models.ExternalReference.html","topicHref":"CycloneDX.Models.ExternalReference.html","topicUid":"CycloneDX.Models.ExternalReference","type":"Class"},{"name":"ExternalReference.ExternalReferenceType","href":"CycloneDX.Models.ExternalReference.ExternalReferenceType.html","topicHref":"CycloneDX.Models.ExternalReference.ExternalReferenceType.html","topicUid":"CycloneDX.Models.ExternalReference.ExternalReferenceType","type":"Enum"},{"name":"Formula","href":"CycloneDX.Models.Formula.html","topicHref":"CycloneDX.Models.Formula.html","topicUid":"CycloneDX.Models.Formula","type":"Class"},{"name":"GraphicsCollection","href":"CycloneDX.Models.GraphicsCollection.html","topicHref":"CycloneDX.Models.GraphicsCollection.html","topicUid":"CycloneDX.Models.GraphicsCollection","type":"Class"},{"name":"GraphicsCollection.Graphic","href":"CycloneDX.Models.GraphicsCollection.Graphic.html","topicHref":"CycloneDX.Models.GraphicsCollection.Graphic.html","topicUid":"CycloneDX.Models.GraphicsCollection.Graphic","type":"Class"},{"name":"Hash","href":"CycloneDX.Models.Hash.html","topicHref":"CycloneDX.Models.Hash.html","topicUid":"CycloneDX.Models.Hash","type":"Class"},{"name":"Hash.HashAlgorithm","href":"CycloneDX.Models.Hash.HashAlgorithm.html","topicHref":"CycloneDX.Models.Hash.HashAlgorithm.html","topicUid":"CycloneDX.Models.Hash.HashAlgorithm","type":"Enum"},{"name":"IHasBomRef","href":"CycloneDX.Models.IHasBomRef.html","topicHref":"CycloneDX.Models.IHasBomRef.html","topicUid":"CycloneDX.Models.IHasBomRef","type":"Interface"},{"name":"IdentifiableAction","href":"CycloneDX.Models.IdentifiableAction.html","topicHref":"CycloneDX.Models.IdentifiableAction.html","topicUid":"CycloneDX.Models.IdentifiableAction","type":"Class"},{"name":"Input","href":"CycloneDX.Models.Input.html","topicHref":"CycloneDX.Models.Input.html","topicUid":"CycloneDX.Models.Input","type":"Class"},{"name":"Issue","href":"CycloneDX.Models.Issue.html","topicHref":"CycloneDX.Models.Issue.html","topicUid":"CycloneDX.Models.Issue","type":"Class"},{"name":"Issue.IssueClassification","href":"CycloneDX.Models.Issue.IssueClassification.html","topicHref":"CycloneDX.Models.Issue.IssueClassification.html","topicUid":"CycloneDX.Models.Issue.IssueClassification","type":"Enum"},{"name":"KeyTypeIndicator","href":"CycloneDX.Models.KeyTypeIndicator.html","topicHref":"CycloneDX.Models.KeyTypeIndicator.html","topicUid":"CycloneDX.Models.KeyTypeIndicator","type":"Enum"},{"name":"Level","href":"CycloneDX.Models.Level.html","topicHref":"CycloneDX.Models.Level.html","topicUid":"CycloneDX.Models.Level","type":"Class"},{"name":"License","href":"CycloneDX.Models.License.html","topicHref":"CycloneDX.Models.License.html","topicUid":"CycloneDX.Models.License","type":"Class"},{"name":"LicenseAcknowledgementEnumeration","href":"CycloneDX.Models.LicenseAcknowledgementEnumeration.html","topicHref":"CycloneDX.Models.LicenseAcknowledgementEnumeration.html","topicUid":"CycloneDX.Models.LicenseAcknowledgementEnumeration","type":"Enum"},{"name":"LicenseChoice","href":"CycloneDX.Models.LicenseChoice.html","topicHref":"CycloneDX.Models.LicenseChoice.html","topicUid":"CycloneDX.Models.LicenseChoice","type":"Class"},{"name":"LicenseChoiceList","href":"CycloneDX.Models.LicenseChoiceList.html","topicHref":"CycloneDX.Models.LicenseChoiceList.html","topicUid":"CycloneDX.Models.LicenseChoiceList","type":"Class"},{"name":"Licensing","href":"CycloneDX.Models.Licensing.html","topicHref":"CycloneDX.Models.Licensing.html","topicUid":"CycloneDX.Models.Licensing","type":"Class"},{"name":"Licensing.LicenseType","href":"CycloneDX.Models.Licensing.LicenseType.html","topicHref":"CycloneDX.Models.Licensing.LicenseType.html","topicUid":"CycloneDX.Models.Licensing.LicenseType","type":"Enum"},{"name":"Lifecycles","href":"CycloneDX.Models.Lifecycles.html","topicHref":"CycloneDX.Models.Lifecycles.html","topicUid":"CycloneDX.Models.Lifecycles","type":"Class"},{"name":"Lifecycles.LifecyclePhase","href":"CycloneDX.Models.Lifecycles.LifecyclePhase.html","topicHref":"CycloneDX.Models.Lifecycles.LifecyclePhase.html","topicUid":"CycloneDX.Models.Lifecycles.LifecyclePhase","type":"Enum"},{"name":"Map","href":"CycloneDX.Models.Map.html","topicHref":"CycloneDX.Models.Map.html","topicUid":"CycloneDX.Models.Map","type":"Class"},{"name":"Metadata","href":"CycloneDX.Models.Metadata.html","topicHref":"CycloneDX.Models.Metadata.html","topicUid":"CycloneDX.Models.Metadata","type":"Class"},{"name":"ModelCard","href":"CycloneDX.Models.ModelCard.html","topicHref":"CycloneDX.Models.ModelCard.html","topicUid":"CycloneDX.Models.ModelCard","type":"Class"},{"name":"ModelCard.ModelCardQuantitativeAnalysis","href":"CycloneDX.Models.ModelCard.ModelCardQuantitativeAnalysis.html","topicHref":"CycloneDX.Models.ModelCard.ModelCardQuantitativeAnalysis.html","topicUid":"CycloneDX.Models.ModelCard.ModelCardQuantitativeAnalysis","type":"Class"},{"name":"ModelCard.ModelCardQuantitativeAnalysis.PerformanceMetric","href":"CycloneDX.Models.ModelCard.ModelCardQuantitativeAnalysis.PerformanceMetric.html","topicHref":"CycloneDX.Models.ModelCard.ModelCardQuantitativeAnalysis.PerformanceMetric.html","topicUid":"CycloneDX.Models.ModelCard.ModelCardQuantitativeAnalysis.PerformanceMetric","type":"Class"},{"name":"ModelCard.ModelCardQuantitativeAnalysis.PerformanceMetric.PerformanceMetricConfidenceInterval","href":"CycloneDX.Models.ModelCard.ModelCardQuantitativeAnalysis.PerformanceMetric.PerformanceMetricConfidenceInterval.html","topicHref":"CycloneDX.Models.ModelCard.ModelCardQuantitativeAnalysis.PerformanceMetric.PerformanceMetricConfidenceInterval.html","topicUid":"CycloneDX.Models.ModelCard.ModelCardQuantitativeAnalysis.PerformanceMetric.PerformanceMetricConfidenceInterval","type":"Class"},{"name":"ModelCard.ModelParameterApproachType","href":"CycloneDX.Models.ModelCard.ModelParameterApproachType.html","topicHref":"CycloneDX.Models.ModelCard.ModelParameterApproachType.html","topicUid":"CycloneDX.Models.ModelCard.ModelParameterApproachType","type":"Enum"},{"name":"ModelCardConsiderations","href":"CycloneDX.Models.ModelCardConsiderations.html","topicHref":"CycloneDX.Models.ModelCardConsiderations.html","topicUid":"CycloneDX.Models.ModelCardConsiderations","type":"Class"},{"name":"ModelCardConsiderations.ModelCardEnvironmentalConsideration","href":"CycloneDX.Models.ModelCardConsiderations.ModelCardEnvironmentalConsideration.html","topicHref":"CycloneDX.Models.ModelCardConsiderations.ModelCardEnvironmentalConsideration.html","topicUid":"CycloneDX.Models.ModelCardConsiderations.ModelCardEnvironmentalConsideration","type":"Class"},{"name":"ModelCardConsiderations.ModelCardEthicalConsideration","href":"CycloneDX.Models.ModelCardConsiderations.ModelCardEthicalConsideration.html","topicHref":"CycloneDX.Models.ModelCardConsiderations.ModelCardEthicalConsideration.html","topicUid":"CycloneDX.Models.ModelCardConsiderations.ModelCardEthicalConsideration","type":"Class"},{"name":"ModelCardConsiderations.ModelCardFairnessAssessment","href":"CycloneDX.Models.ModelCardConsiderations.ModelCardFairnessAssessment.html","topicHref":"CycloneDX.Models.ModelCardConsiderations.ModelCardFairnessAssessment.html","topicUid":"CycloneDX.Models.ModelCardConsiderations.ModelCardFairnessAssessment","type":"Class"},{"name":"ModelParameters","href":"CycloneDX.Models.ModelParameters.html","topicHref":"CycloneDX.Models.ModelParameters.html","topicUid":"CycloneDX.Models.ModelParameters","type":"Class"},{"name":"ModelParameters.MachineLearningInputOutputParameter","href":"CycloneDX.Models.ModelParameters.MachineLearningInputOutputParameter.html","topicHref":"CycloneDX.Models.ModelParameters.MachineLearningInputOutputParameter.html","topicUid":"CycloneDX.Models.ModelParameters.MachineLearningInputOutputParameter","type":"Class"},{"name":"ModelParameters.ModelApproach","href":"CycloneDX.Models.ModelParameters.ModelApproach.html","topicHref":"CycloneDX.Models.ModelParameters.ModelApproach.html","topicUid":"CycloneDX.Models.ModelParameters.ModelApproach","type":"Class"},{"name":"ModelParameters.ModelDataset","href":"CycloneDX.Models.ModelParameters.ModelDataset.html","topicHref":"CycloneDX.Models.ModelParameters.ModelDataset.html","topicUid":"CycloneDX.Models.ModelParameters.ModelDataset","type":"Class"},{"name":"Note","href":"CycloneDX.Models.Note.html","topicHref":"CycloneDX.Models.Note.html","topicUid":"CycloneDX.Models.Note","type":"Class"},{"name":"OrganizationalContact","href":"CycloneDX.Models.OrganizationalContact.html","topicHref":"CycloneDX.Models.OrganizationalContact.html","topicUid":"CycloneDX.Models.OrganizationalContact","type":"Class"},{"name":"OrganizationalEntity","href":"CycloneDX.Models.OrganizationalEntity.html","topicHref":"CycloneDX.Models.OrganizationalEntity.html","topicUid":"CycloneDX.Models.OrganizationalEntity","type":"Class"},{"name":"OrganizationalEntityOrContact","href":"CycloneDX.Models.OrganizationalEntityOrContact.html","topicHref":"CycloneDX.Models.OrganizationalEntityOrContact.html","topicUid":"CycloneDX.Models.OrganizationalEntityOrContact","type":"Class"},{"name":"Output","href":"CycloneDX.Models.Output.html","topicHref":"CycloneDX.Models.Output.html","topicUid":"CycloneDX.Models.Output","type":"Class"},{"name":"Output.OutputType","href":"CycloneDX.Models.Output.OutputType.html","topicHref":"CycloneDX.Models.Output.OutputType.html","topicUid":"CycloneDX.Models.Output.OutputType","type":"Enum"},{"name":"Parameter","href":"CycloneDX.Models.Parameter.html","topicHref":"CycloneDX.Models.Parameter.html","topicUid":"CycloneDX.Models.Parameter","type":"Class"},{"name":"Patch","href":"CycloneDX.Models.Patch.html","topicHref":"CycloneDX.Models.Patch.html","topicUid":"CycloneDX.Models.Patch","type":"Class"},{"name":"Patch.PatchClassification","href":"CycloneDX.Models.Patch.PatchClassification.html","topicHref":"CycloneDX.Models.Patch.PatchClassification.html","topicUid":"CycloneDX.Models.Patch.PatchClassification","type":"Enum"},{"name":"Pedigree","href":"CycloneDX.Models.Pedigree.html","topicHref":"CycloneDX.Models.Pedigree.html","topicUid":"CycloneDX.Models.Pedigree","type":"Class"},{"name":"PostalAddress","href":"CycloneDX.Models.PostalAddress.html","topicHref":"CycloneDX.Models.PostalAddress.html","topicUid":"CycloneDX.Models.PostalAddress","type":"Class"},{"name":"Property","href":"CycloneDX.Models.Property.html","topicHref":"CycloneDX.Models.Property.html","topicUid":"CycloneDX.Models.Property","type":"Class"},{"name":"ProtobufTools","href":"CycloneDX.Models.ProtobufTools.html","topicHref":"CycloneDX.Models.ProtobufTools.html","topicUid":"CycloneDX.Models.ProtobufTools","type":"Class"},{"name":"Provides","href":"CycloneDX.Models.Provides.html","topicHref":"CycloneDX.Models.Provides.html","topicUid":"CycloneDX.Models.Provides","type":"Class"},{"name":"PublicKey","href":"CycloneDX.Models.PublicKey.html","topicHref":"CycloneDX.Models.PublicKey.html","topicUid":"CycloneDX.Models.PublicKey","type":"Class"},{"name":"ReleaseNotes","href":"CycloneDX.Models.ReleaseNotes.html","topicHref":"CycloneDX.Models.ReleaseNotes.html","topicUid":"CycloneDX.Models.ReleaseNotes","type":"Class"},{"name":"Requirement","href":"CycloneDX.Models.Requirement.html","topicHref":"CycloneDX.Models.Requirement.html","topicUid":"CycloneDX.Models.Requirement","type":"Class"},{"name":"ResourceReferenceChoice","href":"CycloneDX.Models.ResourceReferenceChoice.html","topicHref":"CycloneDX.Models.ResourceReferenceChoice.html","topicUid":"CycloneDX.Models.ResourceReferenceChoice","type":"Class"},{"name":"ResourceReferenceChoices","href":"CycloneDX.Models.ResourceReferenceChoices.html","topicHref":"CycloneDX.Models.ResourceReferenceChoices.html","topicUid":"CycloneDX.Models.ResourceReferenceChoices","type":"Class"},{"name":"Service","href":"CycloneDX.Models.Service.html","topicHref":"CycloneDX.Models.Service.html","topicUid":"CycloneDX.Models.Service","type":"Class"},{"name":"ServiceDataChoices","href":"CycloneDX.Models.ServiceDataChoices.html","topicHref":"CycloneDX.Models.ServiceDataChoices.html","topicUid":"CycloneDX.Models.ServiceDataChoices","type":"Class"},{"name":"Signatory","href":"CycloneDX.Models.Signatory.html","topicHref":"CycloneDX.Models.Signatory.html","topicUid":"CycloneDX.Models.Signatory","type":"Class"},{"name":"Signature","href":"CycloneDX.Models.Signature.html","topicHref":"CycloneDX.Models.Signature.html","topicUid":"CycloneDX.Models.Signature","type":"Class"},{"name":"SignatureChoice","href":"CycloneDX.Models.SignatureChoice.html","topicHref":"CycloneDX.Models.SignatureChoice.html","topicUid":"CycloneDX.Models.SignatureChoice","type":"Class"},{"name":"Source","href":"CycloneDX.Models.Source.html","topicHref":"CycloneDX.Models.Source.html","topicUid":"CycloneDX.Models.Source","type":"Class"},{"name":"Standard","href":"CycloneDX.Models.Standard.html","topicHref":"CycloneDX.Models.Standard.html","topicUid":"CycloneDX.Models.Standard","type":"Class"},{"name":"StandardsType","href":"CycloneDX.Models.StandardsType.html","topicHref":"CycloneDX.Models.StandardsType.html","topicUid":"CycloneDX.Models.StandardsType","type":"Class"},{"name":"Step","href":"CycloneDX.Models.Step.html","topicHref":"CycloneDX.Models.Step.html","topicUid":"CycloneDX.Models.Step","type":"Class"},{"name":"Swid","href":"CycloneDX.Models.Swid.html","topicHref":"CycloneDX.Models.Swid.html","topicUid":"CycloneDX.Models.Swid","type":"Class"},{"name":"Targets","href":"CycloneDX.Models.Targets.html","topicHref":"CycloneDX.Models.Targets.html","topicUid":"CycloneDX.Models.Targets","type":"Class"},{"name":"Tool","href":"CycloneDX.Models.Tool.html","topicHref":"CycloneDX.Models.Tool.html","topicUid":"CycloneDX.Models.Tool","type":"Class"},{"name":"ToolChoices","href":"CycloneDX.Models.ToolChoices.html","topicHref":"CycloneDX.Models.ToolChoices.html","topicUid":"CycloneDX.Models.ToolChoices","type":"Class"},{"name":"Trigger","href":"CycloneDX.Models.Trigger.html","topicHref":"CycloneDX.Models.Trigger.html","topicUid":"CycloneDX.Models.Trigger","type":"Class"},{"name":"Trigger.Condition","href":"CycloneDX.Models.Trigger.Condition.html","topicHref":"CycloneDX.Models.Trigger.Condition.html","topicUid":"CycloneDX.Models.Trigger.Condition","type":"Class"},{"name":"Trigger.TriggerType","href":"CycloneDX.Models.Trigger.TriggerType.html","topicHref":"CycloneDX.Models.Trigger.TriggerType.html","topicUid":"CycloneDX.Models.Trigger.TriggerType","type":"Enum"},{"name":"ValidationResult","href":"CycloneDX.Models.ValidationResult.html","topicHref":"CycloneDX.Models.ValidationResult.html","topicUid":"CycloneDX.Models.ValidationResult","type":"Class"},{"name":"Volume","href":"CycloneDX.Models.Volume.html","topicHref":"CycloneDX.Models.Volume.html","topicUid":"CycloneDX.Models.Volume","type":"Class"},{"name":"Volume.VolumeMode","href":"CycloneDX.Models.Volume.VolumeMode.html","topicHref":"CycloneDX.Models.Volume.VolumeMode.html","topicUid":"CycloneDX.Models.Volume.VolumeMode","type":"Enum"},{"name":"Workflow","href":"CycloneDX.Models.Workflow.html","topicHref":"CycloneDX.Models.Workflow.html","topicUid":"CycloneDX.Models.Workflow","type":"Class"},{"name":"WorkflowTask","href":"CycloneDX.Models.WorkflowTask.html","topicHref":"CycloneDX.Models.WorkflowTask.html","topicUid":"CycloneDX.Models.WorkflowTask","type":"Class"},{"name":"WorkflowTask.TaskType","href":"CycloneDX.Models.WorkflowTask.TaskType.html","topicHref":"CycloneDX.Models.WorkflowTask.TaskType.html","topicUid":"CycloneDX.Models.WorkflowTask.TaskType","type":"Enum"},{"name":"Workspace","href":"CycloneDX.Models.Workspace.html","topicHref":"CycloneDX.Models.Workspace.html","topicUid":"CycloneDX.Models.Workspace","type":"Class"},{"name":"Workspace.AccessModeType","href":"CycloneDX.Models.Workspace.AccessModeType.html","topicHref":"CycloneDX.Models.Workspace.AccessModeType.html","topicUid":"CycloneDX.Models.Workspace.AccessModeType","type":"Enum"}]},{"name":"CycloneDX.Models.Vulnerabilities","href":"CycloneDX.Models.Vulnerabilities.html","topicHref":"CycloneDX.Models.Vulnerabilities.html","topicUid":"CycloneDX.Models.Vulnerabilities","type":"Namespace","items":[{"name":"Advisory","href":"CycloneDX.Models.Vulnerabilities.Advisory.html","topicHref":"CycloneDX.Models.Vulnerabilities.Advisory.html","topicUid":"CycloneDX.Models.Vulnerabilities.Advisory","type":"Class"},{"name":"AffectedVersions","href":"CycloneDX.Models.Vulnerabilities.AffectedVersions.html","topicHref":"CycloneDX.Models.Vulnerabilities.AffectedVersions.html","topicUid":"CycloneDX.Models.Vulnerabilities.AffectedVersions","type":"Class"},{"name":"Affects","href":"CycloneDX.Models.Vulnerabilities.Affects.html","topicHref":"CycloneDX.Models.Vulnerabilities.Affects.html","topicUid":"CycloneDX.Models.Vulnerabilities.Affects","type":"Class"},{"name":"Analysis","href":"CycloneDX.Models.Vulnerabilities.Analysis.html","topicHref":"CycloneDX.Models.Vulnerabilities.Analysis.html","topicUid":"CycloneDX.Models.Vulnerabilities.Analysis","type":"Class"},{"name":"Credits","href":"CycloneDX.Models.Vulnerabilities.Credits.html","topicHref":"CycloneDX.Models.Vulnerabilities.Credits.html","topicUid":"CycloneDX.Models.Vulnerabilities.Credits","type":"Class"},{"name":"ImpactAnalysisJustification","href":"CycloneDX.Models.Vulnerabilities.ImpactAnalysisJustification.html","topicHref":"CycloneDX.Models.Vulnerabilities.ImpactAnalysisJustification.html","topicUid":"CycloneDX.Models.Vulnerabilities.ImpactAnalysisJustification","type":"Enum"},{"name":"ImpactAnalysisState","href":"CycloneDX.Models.Vulnerabilities.ImpactAnalysisState.html","topicHref":"CycloneDX.Models.Vulnerabilities.ImpactAnalysisState.html","topicUid":"CycloneDX.Models.Vulnerabilities.ImpactAnalysisState","type":"Enum"},{"name":"ProofOfConcept","href":"CycloneDX.Models.Vulnerabilities.ProofOfConcept.html","topicHref":"CycloneDX.Models.Vulnerabilities.ProofOfConcept.html","topicUid":"CycloneDX.Models.Vulnerabilities.ProofOfConcept","type":"Class"},{"name":"Rating","href":"CycloneDX.Models.Vulnerabilities.Rating.html","topicHref":"CycloneDX.Models.Vulnerabilities.Rating.html","topicUid":"CycloneDX.Models.Vulnerabilities.Rating","type":"Class"},{"name":"Reference","href":"CycloneDX.Models.Vulnerabilities.Reference.html","topicHref":"CycloneDX.Models.Vulnerabilities.Reference.html","topicUid":"CycloneDX.Models.Vulnerabilities.Reference","type":"Class"},{"name":"Response","href":"CycloneDX.Models.Vulnerabilities.Response.html","topicHref":"CycloneDX.Models.Vulnerabilities.Response.html","topicUid":"CycloneDX.Models.Vulnerabilities.Response","type":"Enum"},{"name":"ScoreMethod","href":"CycloneDX.Models.Vulnerabilities.ScoreMethod.html","topicHref":"CycloneDX.Models.Vulnerabilities.ScoreMethod.html","topicUid":"CycloneDX.Models.Vulnerabilities.ScoreMethod","type":"Enum"},{"name":"Severity","href":"CycloneDX.Models.Vulnerabilities.Severity.html","topicHref":"CycloneDX.Models.Vulnerabilities.Severity.html","topicUid":"CycloneDX.Models.Vulnerabilities.Severity","type":"Enum"},{"name":"Status","href":"CycloneDX.Models.Vulnerabilities.Status.html","topicHref":"CycloneDX.Models.Vulnerabilities.Status.html","topicUid":"CycloneDX.Models.Vulnerabilities.Status","type":"Enum"},{"name":"Vulnerability","href":"CycloneDX.Models.Vulnerabilities.Vulnerability.html","topicHref":"CycloneDX.Models.Vulnerabilities.Vulnerability.html","topicUid":"CycloneDX.Models.Vulnerabilities.Vulnerability","type":"Class"}]},{"name":"CycloneDX.Protobuf","href":"CycloneDX.Protobuf.html","topicHref":"CycloneDX.Protobuf.html","topicUid":"CycloneDX.Protobuf","type":"Namespace","items":[{"name":"Serializer","href":"CycloneDX.Protobuf.Serializer.html","topicHref":"CycloneDX.Protobuf.Serializer.html","topicUid":"CycloneDX.Protobuf.Serializer","type":"Class"}]},{"name":"CycloneDX.Spdx","href":"CycloneDX.Spdx.html","topicHref":"CycloneDX.Spdx.html","topicUid":"CycloneDX.Spdx","type":"Namespace","items":[{"name":"PropertyTaxonomy","href":"CycloneDX.Spdx.PropertyTaxonomy.html","topicHref":"CycloneDX.Spdx.PropertyTaxonomy.html","topicUid":"CycloneDX.Spdx.PropertyTaxonomy","type":"Class"}]},{"name":"CycloneDX.Spdx.Interop","href":"CycloneDX.Spdx.Interop.html","topicHref":"CycloneDX.Spdx.Interop.html","topicUid":"CycloneDX.Spdx.Interop","type":"Namespace","items":[{"name":"SpdxDocumentConverters","href":"CycloneDX.Spdx.Interop.SpdxDocumentConverters.html","topicHref":"CycloneDX.Spdx.Interop.SpdxDocumentConverters.html","topicUid":"CycloneDX.Spdx.Interop.SpdxDocumentConverters","type":"Class"}]},{"name":"CycloneDX.Spdx.Interop.Helpers","href":"CycloneDX.Spdx.Interop.Helpers.html","topicHref":"CycloneDX.Spdx.Interop.Helpers.html","topicUid":"CycloneDX.Spdx.Interop.Helpers","type":"Namespace","items":[{"name":"AttributionTexts","href":"CycloneDX.Spdx.Interop.Helpers.AttributionTexts.html","topicHref":"CycloneDX.Spdx.Interop.Helpers.AttributionTexts.html","topicUid":"CycloneDX.Spdx.Interop.Helpers.AttributionTexts","type":"Class"},{"name":"Checksums","href":"CycloneDX.Spdx.Interop.Helpers.Checksums.html","topicHref":"CycloneDX.Spdx.Interop.Helpers.Checksums.html","topicUid":"CycloneDX.Spdx.Interop.Helpers.Checksums","type":"Class"},{"name":"Creators","href":"CycloneDX.Spdx.Interop.Helpers.Creators.html","topicHref":"CycloneDX.Spdx.Interop.Helpers.Creators.html","topicUid":"CycloneDX.Spdx.Interop.Helpers.Creators","type":"Class"},{"name":"CycloneDXBomHelpers","href":"CycloneDX.Spdx.Interop.Helpers.CycloneDXBomHelpers.html","topicHref":"CycloneDX.Spdx.Interop.Helpers.CycloneDXBomHelpers.html","topicUid":"CycloneDX.Spdx.Interop.Helpers.CycloneDXBomHelpers","type":"Class"},{"name":"ExternalRefs","href":"CycloneDX.Spdx.Interop.Helpers.ExternalRefs.html","topicHref":"CycloneDX.Spdx.Interop.Helpers.ExternalRefs.html","topicUid":"CycloneDX.Spdx.Interop.Helpers.ExternalRefs","type":"Class"},{"name":"Files","href":"CycloneDX.Spdx.Interop.Helpers.Files.html","topicHref":"CycloneDX.Spdx.Interop.Helpers.Files.html","topicUid":"CycloneDX.Spdx.Interop.Helpers.Files","type":"Class"},{"name":"General","href":"CycloneDX.Spdx.Interop.Helpers.General.html","topicHref":"CycloneDX.Spdx.Interop.Helpers.General.html","topicUid":"CycloneDX.Spdx.Interop.Helpers.General","type":"Class"},{"name":"SpdxDocumentHelpers","href":"CycloneDX.Spdx.Interop.Helpers.SpdxDocumentHelpers.html","topicHref":"CycloneDX.Spdx.Interop.Helpers.SpdxDocumentHelpers.html","topicUid":"CycloneDX.Spdx.Interop.Helpers.SpdxDocumentHelpers","type":"Class"}]},{"name":"CycloneDX.Spdx.Models","href":"CycloneDX.Spdx.Models.html","topicHref":"CycloneDX.Spdx.Models.html","topicUid":"CycloneDX.Spdx.Models","type":"Namespace","items":[{"name":"ValidationResult","href":"CycloneDX.Spdx.Models.ValidationResult.html","topicHref":"CycloneDX.Spdx.Models.ValidationResult.html","topicUid":"CycloneDX.Spdx.Models.ValidationResult","type":"Class"}]},{"name":"CycloneDX.Spdx.Models.v2_3","href":"CycloneDX.Spdx.Models.v2_3.html","topicHref":"CycloneDX.Spdx.Models.v2_3.html","topicUid":"CycloneDX.Spdx.Models.v2_3","type":"Namespace","items":[{"name":"Annotation","href":"CycloneDX.Spdx.Models.v2_3.Annotation.html","topicHref":"CycloneDX.Spdx.Models.v2_3.Annotation.html","topicUid":"CycloneDX.Spdx.Models.v2_3.Annotation","type":"Class"},{"name":"AnnotationType","href":"CycloneDX.Spdx.Models.v2_3.AnnotationType.html","topicHref":"CycloneDX.Spdx.Models.v2_3.AnnotationType.html","topicUid":"CycloneDX.Spdx.Models.v2_3.AnnotationType","type":"Enum"},{"name":"Checksum","href":"CycloneDX.Spdx.Models.v2_3.Checksum.html","topicHref":"CycloneDX.Spdx.Models.v2_3.Checksum.html","topicUid":"CycloneDX.Spdx.Models.v2_3.Checksum","type":"Class"},{"name":"ChecksumAlgorithm","href":"CycloneDX.Spdx.Models.v2_3.ChecksumAlgorithm.html","topicHref":"CycloneDX.Spdx.Models.v2_3.ChecksumAlgorithm.html","topicUid":"CycloneDX.Spdx.Models.v2_3.ChecksumAlgorithm","type":"Enum"},{"name":"CreationInfo","href":"CycloneDX.Spdx.Models.v2_3.CreationInfo.html","topicHref":"CycloneDX.Spdx.Models.v2_3.CreationInfo.html","topicUid":"CycloneDX.Spdx.Models.v2_3.CreationInfo","type":"Class"},{"name":"CrossRef","href":"CycloneDX.Spdx.Models.v2_3.CrossRef.html","topicHref":"CycloneDX.Spdx.Models.v2_3.CrossRef.html","topicUid":"CycloneDX.Spdx.Models.v2_3.CrossRef","type":"Class"},{"name":"ExternalDocumentRef","href":"CycloneDX.Spdx.Models.v2_3.ExternalDocumentRef.html","topicHref":"CycloneDX.Spdx.Models.v2_3.ExternalDocumentRef.html","topicUid":"CycloneDX.Spdx.Models.v2_3.ExternalDocumentRef","type":"Class"},{"name":"ExternalRef","href":"CycloneDX.Spdx.Models.v2_3.ExternalRef.html","topicHref":"CycloneDX.Spdx.Models.v2_3.ExternalRef.html","topicUid":"CycloneDX.Spdx.Models.v2_3.ExternalRef","type":"Class"},{"name":"ExternalRefCategory","href":"CycloneDX.Spdx.Models.v2_3.ExternalRefCategory.html","topicHref":"CycloneDX.Spdx.Models.v2_3.ExternalRefCategory.html","topicUid":"CycloneDX.Spdx.Models.v2_3.ExternalRefCategory","type":"Enum"},{"name":"ExtractedLicensingInfo","href":"CycloneDX.Spdx.Models.v2_3.ExtractedLicensingInfo.html","topicHref":"CycloneDX.Spdx.Models.v2_3.ExtractedLicensingInfo.html","topicUid":"CycloneDX.Spdx.Models.v2_3.ExtractedLicensingInfo","type":"Class"},{"name":"File","href":"CycloneDX.Spdx.Models.v2_3.File.html","topicHref":"CycloneDX.Spdx.Models.v2_3.File.html","topicUid":"CycloneDX.Spdx.Models.v2_3.File","type":"Class"},{"name":"FileType","href":"CycloneDX.Spdx.Models.v2_3.FileType.html","topicHref":"CycloneDX.Spdx.Models.v2_3.FileType.html","topicUid":"CycloneDX.Spdx.Models.v2_3.FileType","type":"Enum"},{"name":"Package","href":"CycloneDX.Spdx.Models.v2_3.Package.html","topicHref":"CycloneDX.Spdx.Models.v2_3.Package.html","topicUid":"CycloneDX.Spdx.Models.v2_3.Package","type":"Class"},{"name":"PackageVerificationCode","href":"CycloneDX.Spdx.Models.v2_3.PackageVerificationCode.html","topicHref":"CycloneDX.Spdx.Models.v2_3.PackageVerificationCode.html","topicUid":"CycloneDX.Spdx.Models.v2_3.PackageVerificationCode","type":"Class"},{"name":"PrimaryPackagePurposeType","href":"CycloneDX.Spdx.Models.v2_3.PrimaryPackagePurposeType.html","topicHref":"CycloneDX.Spdx.Models.v2_3.PrimaryPackagePurposeType.html","topicUid":"CycloneDX.Spdx.Models.v2_3.PrimaryPackagePurposeType","type":"Enum"},{"name":"Range","href":"CycloneDX.Spdx.Models.v2_3.Range.html","topicHref":"CycloneDX.Spdx.Models.v2_3.Range.html","topicUid":"CycloneDX.Spdx.Models.v2_3.Range","type":"Class"},{"name":"RangePointer","href":"CycloneDX.Spdx.Models.v2_3.RangePointer.html","topicHref":"CycloneDX.Spdx.Models.v2_3.RangePointer.html","topicUid":"CycloneDX.Spdx.Models.v2_3.RangePointer","type":"Class"},{"name":"Relationship","href":"CycloneDX.Spdx.Models.v2_3.Relationship.html","topicHref":"CycloneDX.Spdx.Models.v2_3.Relationship.html","topicUid":"CycloneDX.Spdx.Models.v2_3.Relationship","type":"Class"},{"name":"RelationshipType","href":"CycloneDX.Spdx.Models.v2_3.RelationshipType.html","topicHref":"CycloneDX.Spdx.Models.v2_3.RelationshipType.html","topicUid":"CycloneDX.Spdx.Models.v2_3.RelationshipType","type":"Enum"},{"name":"ReviewInformation","href":"CycloneDX.Spdx.Models.v2_3.ReviewInformation.html","topicHref":"CycloneDX.Spdx.Models.v2_3.ReviewInformation.html","topicUid":"CycloneDX.Spdx.Models.v2_3.ReviewInformation","type":"Class"},{"name":"Snippet","href":"CycloneDX.Spdx.Models.v2_3.Snippet.html","topicHref":"CycloneDX.Spdx.Models.v2_3.Snippet.html","topicUid":"CycloneDX.Spdx.Models.v2_3.Snippet","type":"Class"},{"name":"SpdxDocument","href":"CycloneDX.Spdx.Models.v2_3.SpdxDocument.html","topicHref":"CycloneDX.Spdx.Models.v2_3.SpdxDocument.html","topicUid":"CycloneDX.Spdx.Models.v2_3.SpdxDocument","type":"Class"},{"name":"UtcDateTimeConverter","href":"CycloneDX.Spdx.Models.v2_3.UtcDateTimeConverter.html","topicHref":"CycloneDX.Spdx.Models.v2_3.UtcDateTimeConverter.html","topicUid":"CycloneDX.Spdx.Models.v2_3.UtcDateTimeConverter","type":"Class"}]},{"name":"CycloneDX.Spdx.Serialization","href":"CycloneDX.Spdx.Serialization.html","topicHref":"CycloneDX.Spdx.Serialization.html","topicUid":"CycloneDX.Spdx.Serialization","type":"Namespace","items":[{"name":"JsonSerializer","href":"CycloneDX.Spdx.Serialization.JsonSerializer.html","topicHref":"CycloneDX.Spdx.Serialization.JsonSerializer.html","topicUid":"CycloneDX.Spdx.Serialization.JsonSerializer","type":"Class"},{"name":"XmlSerializer","href":"CycloneDX.Spdx.Serialization.XmlSerializer.html","topicHref":"CycloneDX.Spdx.Serialization.XmlSerializer.html","topicUid":"CycloneDX.Spdx.Serialization.XmlSerializer","type":"Class"}]},{"name":"CycloneDX.Spdx.Serialization.Converters","href":"CycloneDX.Spdx.Serialization.Converters.html","topicHref":"CycloneDX.Spdx.Serialization.Converters.html","topicUid":"CycloneDX.Spdx.Serialization.Converters","type":"Namespace","items":[{"name":"HyphenToUnderscoreEnumConverter<T>","href":"CycloneDX.Spdx.Serialization.Converters.HyphenToUnderscoreEnumConverter-1.html","topicHref":"CycloneDX.Spdx.Serialization.Converters.HyphenToUnderscoreEnumConverter-1.html","topicUid":"CycloneDX.Spdx.Serialization.Converters.HyphenToUnderscoreEnumConverter`1","type":"Class"}]},{"name":"CycloneDX.Spdx.Validation","href":"CycloneDX.Spdx.Validation.html","topicHref":"CycloneDX.Spdx.Validation.html","topicUid":"CycloneDX.Spdx.Validation","type":"Namespace","items":[{"name":"JsonValidator","href":"CycloneDX.Spdx.Validation.JsonValidator.html","topicHref":"CycloneDX.Spdx.Validation.JsonValidator.html","topicUid":"CycloneDX.Spdx.Validation.JsonValidator","type":"Class"},{"name":"XmlValidator","href":"CycloneDX.Spdx.Validation.XmlValidator.html","topicHref":"CycloneDX.Spdx.Validation.XmlValidator.html","topicUid":"CycloneDX.Spdx.Validation.XmlValidator","type":"Class"}]},{"name":"CycloneDX.Utils","href":"CycloneDX.Utils.html","topicHref":"CycloneDX.Utils.html","topicUid":"CycloneDX.Utils","type":"Namespace","items":[{"name":"CycloneDXUtils","href":"CycloneDX.Utils.CycloneDXUtils.html","topicHref":"CycloneDX.Utils.CycloneDXUtils.html","topicUid":"CycloneDX.Utils.CycloneDXUtils","type":"Class"},{"name":"DiffItem<T>","href":"CycloneDX.Utils.DiffItem-1.html","topicHref":"CycloneDX.Utils.DiffItem-1.html","topicUid":"CycloneDX.Utils.DiffItem`1","type":"Class"},{"name":"ListExtensions","href":"CycloneDX.Utils.ListExtensions.html","topicHref":"CycloneDX.Utils.ListExtensions.html","topicUid":"CycloneDX.Utils.ListExtensions","type":"Class"}]},{"name":"CycloneDX.Utils.Exceptions","href":"CycloneDX.Utils.Exceptions.html","topicHref":"CycloneDX.Utils.Exceptions.html","topicUid":"CycloneDX.Utils.Exceptions","type":"Namespace","items":[{"name":"MissingMetadataComponentException","href":"CycloneDX.Utils.Exceptions.MissingMetadataComponentException.html","topicHref":"CycloneDX.Utils.Exceptions.MissingMetadataComponentException.html","topicUid":"CycloneDX.Utils.Exceptions.MissingMetadataComponentException","type":"Class"}]},{"name":"CycloneDX.Xml","href":"CycloneDX.Xml.html","topicHref":"CycloneDX.Xml.html","topicUid":"CycloneDX.Xml","type":"Namespace","items":[{"name":"Serializer","href":"CycloneDX.Xml.Serializer.html","topicHref":"CycloneDX.Xml.Serializer.html","topicUid":"CycloneDX.Xml.Serializer","type":"Class"},{"name":"Validator","href":"CycloneDX.Xml.Validator.html","topicHref":"CycloneDX.Xml.Validator.html","topicUid":"CycloneDX.Xml.Validator","type":"Class"}]}],"memberLayout":"SamePage"}
